pcdm/__init__.py
pcdm/account.py
pcdm/agreementrole.py
pcdm/assessment.py
pcdm/base.py
pcdm/claim.py
pcdm/claimrole.py
pcdm/event.py
pcdm/insurable.py
pcdm/money.py
pcdm/party.py
pcdm/partyst.py
pcdm/policy.py
pcdm/product.py
pcdm/staffing.py
pcdm-0.1.0.dist-info/LICENSE
pcdm-0.1.0.dist-info/METADATA
pcdm-0.1.0.dist-info/WHEEL
pcdm-0.1.0.dist-info/top_level.txt
pcdm-0.1.0.dist-info/RECORD
