Metadata-Version: 2.1
Name: pcdm
Version: 0.1.0
Summary: Property Casualty Data Model Standard
Home-page: https://github.com/genedan/pcdm
Author: Gene Dan
Author-email: genedan@gmail.com
License: UNKNOWN
Platform: UNKNOWN
Classifier: Programming Language :: Python :: 3.8
Classifier: License :: OSI Approved :: Mozilla Public License 2.0 (MPL 2.0)
Classifier: Operating System :: POSIX :: Linux
Requires-Python: >=3.8
